hydroecolstm/__init__.py
hydroecolstm/model_run.py
hydroecolstm/data/__init__.py
hydroecolstm/data/custom_dataset.py
hydroecolstm/data/read_config.py
hydroecolstm/data/read_data.py
hydroecolstm/data/scaler.py
hydroecolstm/feat_importance/__init__.py
hydroecolstm/feat_importance/perm_feat_importance.py
hydroecolstm/images/model_head_class.png
hydroecolstm/images/parameter_explanation.png
hydroecolstm/interface/__init__.py
hydroecolstm/interface/application_frame.py
hydroecolstm/interface/data_frame.py
hydroecolstm/interface/main_gui.py
hydroecolstm/interface/network_design_frame.py
hydroecolstm/interface/project_summary_frame.py
hydroecolstm/interface/sidebar_frame.py
hydroecolstm/interface/train_test_frame.py
hydroecolstm/interface/utility.py
hydroecolstm/interface/visualize_frame.py
hydroecolstm/model/__init__.py
hydroecolstm/model/create_model.py
hydroecolstm/model/ea_lstm.py
hydroecolstm/model/linears.py
hydroecolstm/model/lstm_linears.py
hydroecolstm/train/__init__.py
hydroecolstm/train/custom_loss.py
hydroecolstm/train/trainer.py
hydroecolstm/utility/__init__.py
hydroecolstm/utility/evaluation_function.py
hydroecolstm/utility/format_conversion.py
hydroecolstm/utility/plot.py
hydroecolstm-0.3.7.dist-info/licenses/LICENSE
hydroecolstm-0.3.7.dist-info/METADATA
hydroecolstm-0.3.7.dist-info/WHEEL
hydroecolstm-0.3.7.dist-info/top_level.txt
hydroecolstm-0.3.7.dist-info/RECORD
