Metadata-Version: 2.4
Name: hydroecolstm
Version: 0.3.7
Summary: A python package for HydroEcological Modelling using LSTM
Home-page: https://github.com/tamnva/hydroecolstm
Author: Tam V. Nguyen
Author-email: tamnva@gmail.com
Classifier: Development Status :: 1 - Planning
Classifier: Intended Audience :: Science/Research
Classifier: License :: OSI Approved :: GNU General Public License v3 (GPLv3)
Classifier: Operating System :: POSIX :: Linux
Classifier: Programming Language :: Python :: 3
Requires-Python: <=3.12
License-File: LICENSE
Requires-Dist: pandas
Requires-Dist: numpy
Requires-Dist: torch
Requires-Dist: pandastable
Requires-Dist: tkcalendar
Requires-Dist: PyYAML
Requires-Dist: pathlib
Requires-Dist: customtkinter
Requires-Dist: CTkToolTip
Requires-Dist: CTkMessagebox
Requires-Dist: CTkListbox
Requires-Dist: matplotlib
Requires-Dist: ray[tune]
Dynamic: author
Dynamic: author-email
Dynamic: classifier
Dynamic: description
Dynamic: description-content-type
Dynamic: home-page
Dynamic: license-file
Dynamic: requires-dist
Dynamic: requires-python
Dynamic: summary
